setup.py
ad_udacity_distributions/Binomialdistribution.py
ad_udacity_distributions/Gaussiandistribution.py
ad_udacity_distributions/Generaldistribution.py
ad_udacity_distributions/__init__.py
ad_udacitydistributions.egg-info/PKG-INFO
ad_udacitydistributions.egg-info/SOURCES.txt
ad_udacitydistributions.egg-info/dependency_links.txt
ad_udacitydistributions.egg-info/not-zip-safe
ad_udacitydistributions.egg-info/top_level.txt