Metadata-Version: 1.0
Name: ad-udacitydistributions
Version: 1.1
Summary: Gaussian and Binomial distributions
Home-page: UNKNOWN
Author: Abdel-Dayane Marcos
Author-email: marcyane7@gmail.com
License: UNKNOWN
Platform: UNKNOWN
